[
  {
    "language": "French",
    "distribution": {
      "c": 0.02994,
      "a": 0.08136,
      "n": 0.0687,
      "d": 0.03604,
      "i": 0.07295,
      "e": 0.17044,
      "o": 0.0567,
      "u": 0.06595,
      "l": 0.05369,
      "p": 0.02671,
      "t": 0.07028,
      "m": 0.03195,
      "s": 0.08014,
      "r": 0.06628,
      "f": 0.01147,
      "h": 0.01073,
      "v": 0.01833,
      "b": 0.00923,
      "q": 0.01212,
      "g": 0.00924,
      "j": 0.00692,
      "x": 0.00468,
      "z": 0.00233,
      "y": 0.00298,
      "w": 0.00034,
      "k": 0.00019,
      "º": 0,
      "œ": 0.00026,
      "æ": 0
    }
  },
  {
    "language": "Latin",
    "distribution": {
      "l": 0.03078,
      "i": 0.10911,
      "b": 0.01423,
      "e": 0.11911,
      "r": 0.06343,
      "p": 0.02686,
      "m": 0.05269,
      "u": 0.08271,
      "s": 0.07597,
      "q": 0.01831,
      "a": 0.08637,
      "t": 0.08384,
      "c": 0.03834,
      "f": 0.01031,
      "n": 0.06402,
      "d": 0.03105,
      "h": 0.00918,
      "o": 0.05502,
      "g": 0.01068,
      "x": 0.00432,
      "v": 0.01119,
      "y": 0.00127,
      "κ": 0,
      "α": 0.00001,
      "τ": 0,
      "ο": 0,
      "ρ": 0,
      "θ": 0,
      "ω": 0,
      "μ": 0,
      "η": 0,
      "ν": 0,
      "π": 0,
      "ε": 0,
      "φ": 0,
      "γ": 0,
      "ι": 0,
      "υ": 0,
      "ξ": 0,
      "σ": 0,
      "k": 0.00018,
      "ς": 0,
      "z": 0.00006,
      "w": 0.00066,
      "æ": 0.00001,
      "j": 0.00027,
      "œ": 0
    }
  },
  {
    "language": "Ancient Greek",
    "distribution": {
      "μ": 0.03253,
      "η": 0.03679,
      "ν": 0.08357,
      "ι": 0.09438,
      "α": 0.10528,
      "ε": 0.09972,
      "δ": 0.02864,
      "θ": 0.01494,
      "π": 0.03362,
      "λ": 0.02995,
      "ω": 0.03036,
      "χ": 0.01015,
      "ο": 0.09592,
      "ς": 0.04019,
      "υ": 0.04468,
      "ρ": 0.03917,
      "ʼ": 0.0018,
      "γ": 0.01661,
      "κ": 0.03131,
      "φ": 0.00946,
      "ψ": 0.00171,
      "τ": 0.06879,
      "σ": 0.03592,
      "β": 0.00516,
      "ξ": 0.00431,
      "ζ": 0.00207,
      "t": 0.00029,
      "h": 0.0001,
      "i": 0.00013,
      "s": 0.00018,
      "e": 0.00048,
      "d": 0.00012,
      "o": 0.00013,
      "n": 0.00012,
      "m": 0.00012,
      "l": 0.00011,
      "w": 0.00004,
      "p": 0.00016,
      "a": 0.00022,
      "r": 0.00032,
      "u": 0.00014,
      "b": 0.00002,
      "c": 0.00007,
      "k": 0.00005,
      "f": 0.00005,
      "g": 0.00003,
      "v": 0.00002,
      "j": 0.00001,
      "y": 0.00002,
      "x": 0,
      "z": 0,
      "ʽ": 0
    }
  },
  {
    "language": "Dutch",
    "distribution": {
      "m": 0.02447,
      "a": 0.07522,
      "x": 0.00044,
      "h": 0.03252,
      "v": 0.02248,
      "e": 0.18684,
      "l": 0.0396,
      "r": 0.05791,
      "o": 0.05795,
      "f": 0.00793,
      "d": 0.05763,
      "k": 0.02176,
      "i": 0.06642,
      "n": 0.09724,
      "g": 0.0313,
      "s": 0.03807,
      "c": 0.01375,
      "t": 0.06241,
      "p": 0.01243,
      "y": 0.00309,
      "u": 0.02178,
      "b": 0.01359,
      "w": 0.01755,
      "j": 0.0178,
      "q": 0.00106,
      "z": 0.01874,
      "º": 0.00001,
      "æ": 0,
      "ƒ": 0,
      "ß": 0
    }
  },
  {
    "language": "English",
    "distribution": {
      "t": 0.09065,
      "h": 0.06393,
      "e": 0.12386,
      "r": 0.05768,
      "a": 0.0797,
      "g": 0.01997,
      "d": 0.0456,
      "y": 0.02109,
      "o": 0.07787,
      "f": 0.02231,
      "m": 0.02741,
      "l": 0.04046,
      "p": 0.01589,
      "i": 0.06838,
      "n": 0.06874,
      "c": 0.02278,
      "k": 0.00781,
      "b": 0.01525,
      "w": 0.02475,
      "s": 0.0624,
      "u": 0.02938,
      "v": 0.00972,
      "æ": 0.00001,
      "q": 0.00105,
      "z": 0.00061,
      "j": 0.00131,
      "x": 0.00139,
      "œ": 0,
      "ח": 0,
      "ו": 0,
      "ϰ": 0,
      "η": 0,
      "τ": 0,
      "ο": 0,
      "ς": 0
    }
  },
  {
    "language": "Italian",
    "distribution": {
      "l": 0.0586,
      "a": 0.11322,
      "d": 0.03608,
      "i": 0.10293,
      "v": 0.02253,
      "n": 0.06964,
      "c": 0.04622,
      "o": 0.0978,
      "m": 0.02902,
      "e": 0.11799,
      "t": 0.05892,
      "g": 0.01785,
      "h": 0.01371,
      "r": 0.06445,
      "f": 0.01108,
      "z": 0.00633,
      "s": 0.05269,
      "p": 0.02853,
      "u": 0.03392,
      "q": 0.00683,
      "b": 0.00971,
      "x": 0.00051,
      "y": 0.0002,
      "j": 0.00023,
      "w": 0.00089,
      "k": 0.00005,
      "º": 0,
      "æ": 0,
      "ο": 0.00001,
      "ν": 0.00001,
      "ι": 0.00001,
      "θ": 0,
      "ε": 0,
      "φ": 0,
      "λ": 0,
      "υ": 0,
      "σ": 0,
      "α": 0,
      "π": 0,
      "η": 0,
      "κ": 0,
      "ς": 0,
      "γ": 0,
      "ρ": 0,
      "ω": 0,
      "μ": 0,
      "τ": 0,
      "р": 0,
      "с": 0,
      "β": 0
    }
  },
  {
    "language": "Spanish",
    "distribution": {
      "e": 0.13352,
      "l": 0.05303,
      "i": 0.06021,
      "n": 0.06803,
      "g": 0.01252,
      "o": 0.09474,
      "s": 0.07418,
      "h": 0.01709,
      "d": 0.0491,
      "a": 0.12072,
      "q": 0.01355,
      "u": 0.04425,
      "j": 0.00504,
      "t": 0.04588,
      "m": 0.03003,
      "c": 0.03552,
      "p": 0.02246,
      "r": 0.06274,
      "v": 0.01122,
      "y": 0.01417,
      "b": 0.01481,
      "f": 0.00811,
      "z": 0.00375,
      "x": 0.00102,
      "w": 0.00298,
      "º": 0.00002,
      "æ": 0.00001,
      "k": 0.00126,
      "œ": 0,
      "ª": 0.00003
    }
  },
  {
    "language": "German",
    "distribution": {
      "f": 0.01512,
      "a": 0.06099,
      "u": 0.04499,
      "s": 0.06259,
      "t": 0.05831,
      "d": 0.05134,
      "e": 0.1611,
      "r": 0.06899,
      "g": 0.02781,
      "o": 0.02515,
      "i": 0.08075,
      "l": 0.03816,
      "b": 0.01849,
      "y": 0.00045,
      "j": 0.00221,
      "h": 0.05872,
      "n": 0.10004,
      "w": 0.01934,
      "v": 0.00704,
      "c": 0.03575,
      "z": 0.01091,
      "p": 0.00563,
      "m": 0.02948,
      "k": 0.01194,
      "x": 0.00024,
      "ß": 0.0043,
      "q": 0.00015,
      "æ": 0
    }
  },
  {
    "language": "Old French",
    "distribution": {
      "i": 0.0857,
      "c": 0.028,
      "a": 0.07527,
      "r": 0.06927,
      "l": 0.05892,
      "e": 0.17387,
      "s": 0.08509,
      "n": 0.07439,
      "o": 0.0567,
      "t": 0.07907,
      "m": 0.02637,
      "p": 0.02065,
      "g": 0.0106,
      "z": 0.00794,
      "u": 0.0506,
      "d": 0.02612,
      "q": 0.01375,
      "k": 0.00065,
      "v": 0.0206,
      "f": 0.01212,
      "h": 0.00839,
      "b": 0.00832,
      "x": 0.0021,
      "j": 0.00434,
      "w": 0.00009,
      "y": 0.00106,
      "œ": 0.00001
    }
  },
  {
    "language": "Hebrew",
    "distribution": {
      "ב": 0.05233,
      "ר": 0.05513,
      "א": 0.06979,
      "ש": 0.04763,
      "י": 0.11086,
      "ת": 0.05152,
      "ל": 0.06948,
      "ה": 0.0848,
      "ם": 0.03514,
      "מ": 0.05262,
      "ו": 0.11404,
      "ץ": 0.00223,
      "ח": 0.02432,
      "ך": 0.00961,
      "ע": 0.03694,
      "פ": 0.01553,
      "נ": 0.03566,
      "כ": 0.02888,
      "ט": 0.00672,
      "ד": 0.02727,
      "ן": 0.01327,
      "ק": 0.0154,
      "ז": 0.00903,
      "צ": 0.01138,
      "ג": 0.00992,
      "ף": 0.00232,
      "ס": 0.00816
    }
  },
  {
    "language": "Arabic",
    "distribution": {
      "ا": 0.17618,
      "س": 0.0212,
      "ق": 0.02521,
      "ي": 0.06694,
      "ن": 0.0607,
      "م": 0.06552,
      "ش": 0.01012,
      "و": 0.06521,
      "ل": 0.11398,
      "ف": 0.02968,
      "د": 0.0268,
      "ى": 0.00998,
      "ط": 0.00796,
      "خ": 0.0084,
      "ر": 0.0451,
      "ة": 0.0164,
      "ع": 0.03638,
      "ك": 0.02387,
      "ص": 0.00961,
      "ت": 0.0303,
      "ه": 0.03624,
      "ب": 0.04263,
      "ح": 0.02028,
      "ث": 0.00494,
      "ذ": 0.01041,
      "ز": 0.00638,
      "ج": 0.01191,
      "غ": 0.00465,
      "ض": 0.00627,
      "ظ": 0.00234,
      "ء": 0.00443
    }
  }
]
